README.md
setup.py
test/test_hil.py
testerinopepperino/__init__.py
testerinopepperino/pepperino.py
testerinopepperino/testerinopepperino.py
testerinopepperino.egg-info/PKG-INFO
testerinopepperino.egg-info/SOURCES.txt
testerinopepperino.egg-info/dependency_links.txt
testerinopepperino.egg-info/top_level.txt