Metadata-Version: 2.1
Name: testerinopepperino
Version: 0.0.21
Summary: testerinopepperinosss
Home-page: UNKNOWN
Author: Willam Nguyen
Author-email: williamvnguyen5@gmail.com
License: UNKNOWN
Keywords: python,test
Platform: UNKNOWN
Classifier: Development Status :: 1 - Planning
Classifier: Intended Audience :: Developers
Classifier: Programming Language :: Python :: 3
Classifier: Operating System :: Unix
Classifier: Operating System :: MacOS :: MacOS X
Classifier: Operating System :: Microsoft :: Windows
